keyhint/__init__.py
keyhint/__main__.py
keyhint/app.py
keyhint/binding.py
keyhint/config.py
keyhint/context.py
keyhint/css.py
keyhint/headerbar.py
keyhint/sheets.py
keyhint/window.py
keyhint/config/alacritty.toml
keyhint/config/cli.toml
keyhint/config/firefox-tridactyl.toml
keyhint/config/firefox.toml
keyhint/config/foot.toml
keyhint/config/forge.toml
keyhint/config/github.toml
keyhint/config/gnome-terminal.toml
keyhint/config/keyhint.toml
keyhint/config/kitty.toml
keyhint/config/pop-shell.toml
keyhint/config/tilix.toml
keyhint/config/tmux.toml
keyhint/config/vim.toml
keyhint/config/vscode-copilot.toml
keyhint/config/vscode-neovim.toml
keyhint/config/vscode.toml
keyhint/resources/headerbar.ui
keyhint/resources/keyhint.png
keyhint/resources/keyhint_128.png
keyhint/resources/keyhint_32.png
keyhint/resources/keyhint_48.png
keyhint/resources/keyhint_64.png
keyhint/resources/keyhint_icon.svg
keyhint/resources/style.css
keyhint/resources/window.ui
keyhint-0.5.6.dist-info/METADATA
keyhint-0.5.6.dist-info/WHEEL
keyhint-0.5.6.dist-info/entry_points.txt
keyhint-0.5.6.dist-info/licenses/LICENSE
keyhint-0.5.6.dist-info/RECORD
