Metadata-Version: 2.4
Name: keyhint
Version: 0.5.6
Summary: Cheat-sheets for shortcuts & commands at your fingertips.
Project-URL: Documentation, https://github.com/dynobo/keyhint#readme
Project-URL: Issues, https://github.com/dynobo/keyhint/issues
Project-URL: Source, https://github.com/dynobo/keyhint
Author-email: dynobo <dynobo@mailbox.org>
License-File: LICENSE
Keywords: cheatsheet,helper,hints,keybindings,shortcuts
Classifier: Development Status :: 4 - Beta
Classifier: Intended Audience :: End Users/Desktop
Classifier: License :: OSI Approved :: MIT License
Classifier: Operating System :: POSIX :: Linux
Classifier: Programming Language :: Python
Classifier: Programming Language :: Python :: 3.11
Classifier: Programming Language :: Python :: 3.12
Classifier: Programming Language :: Python :: Implementation :: CPython
Classifier: Programming Language :: Python :: Implementation :: PyPy
Classifier: Topic :: Utilities
Requires-Python: >=3.11
Requires-Dist: pygobject>=3.42.2
